.gitignore
.travis.yml
CHANGES.txt
LICENSE.txt
README.txt
setup.py
tox.ini
upgrade-resources.sh
js/__init__.py
js.fineuploader.egg-info/PKG-INFO
js.fineuploader.egg-info/SOURCES.txt
js.fineuploader.egg-info/dependency_links.txt
js.fineuploader.egg-info/entry_points.txt
js.fineuploader.egg-info/namespace_packages.txt
js.fineuploader.egg-info/not-zip-safe
js.fineuploader.egg-info/requires.txt
js.fineuploader.egg-info/top_level.txt
js/fineuploader/__init__.py
js/fineuploader/test_fineuploader.txt
js/fineuploader/resources/fine-uploader/continue.gif
js/fineuploader/resources/fine-uploader/edit.gif
js/fineuploader/resources/fine-uploader/fine-uploader-gallery.css
js/fineuploader/resources/fine-uploader/fine-uploader-gallery.min.css
js/fineuploader/resources/fine-uploader/fine-uploader-gallery.min.css.map
js/fineuploader/resources/fine-uploader/fine-uploader-new.css
js/fineuploader/resources/fine-uploader/fine-uploader-new.min.css
js/fineuploader/resources/fine-uploader/fine-uploader-new.min.css.map
js/fineuploader/resources/fine-uploader/fine-uploader.core.js
js/fineuploader/resources/fine-uploader/fine-uploader.core.js.map
js/fineuploader/resources/fine-uploader/fine-uploader.core.min.js
js/fineuploader/resources/fine-uploader/fine-uploader.core.min.js.map
js/fineuploader/resources/fine-uploader/fine-uploader.css
js/fineuploader/resources/fine-uploader/fine-uploader.js
js/fineuploader/resources/fine-uploader/fine-uploader.js.map
js/fineuploader/resources/fine-uploader/fine-uploader.min.css
js/fineuploader/resources/fine-uploader/fine-uploader.min.css.map
js/fineuploader/resources/fine-uploader/fine-uploader.min.js
js/fineuploader/resources/fine-uploader/fine-uploader.min.js.map
js/fineuploader/resources/fine-uploader/iframe.xss.response.js
js/fineuploader/resources/fine-uploader/loading.gif
js/fineuploader/resources/fine-uploader/pause.gif
js/fineuploader/resources/fine-uploader/processing.gif
js/fineuploader/resources/fine-uploader/retry.gif
js/fineuploader/resources/fine-uploader/trash.gif
js/fineuploader/resources/fine-uploader/placeholders/not_available-generic.png
js/fineuploader/resources/fine-uploader/placeholders/waiting-generic.png
js/fineuploader/resources/fine-uploader/templates/default.html
js/fineuploader/resources/fine-uploader/templates/gallery.html
